README.txt
setup.py
libLAS.egg-info/PKG-INFO
libLAS.egg-info/SOURCES.txt
libLAS.egg-info/dependency_links.txt
libLAS.egg-info/not-zip-safe
libLAS.egg-info/requires.txt
libLAS.egg-info/top_level.txt
liblas/__init__.py
liblas/color.py
liblas/core.py
liblas/file.py
liblas/guid.py
liblas/header.py
liblas/point.py
liblas/schema.py
liblas/srs.py
liblas/vlr.py