Metadata-Version: 1.1
Name: libLAS
Version: 1.8.1
Summary: LAS 1.0/1.1/1.2 LiDAR data format translation
Home-page: http://liblas.org
Author: Howard Butler
Author-email: hobu.inc@gmail.com
License: BSD
Keywords: DEM elevation LIDAR
Platform: UNKNOWN
Classifier: Development Status :: 5 - Production/Stable
Classifier: Intended Audience :: Developers
Classifier: Intended Audience :: Science/Research
Classifier: License :: OSI Approved :: BSD License
Classifier: Operating System :: OS Independent
Classifier: Programming Language :: Python
Classifier: Topic :: Scientific/Engineering :: GIS
